[
  { "Class": 1, "ClassNameEn": "ItemClass_name_1" },
  { "Class": 2, "ClassNameEn": "ItemClass_name_2" },
  { "Class": 3, "ClassNameEn": "ItemClass_name_3" },
  { "Class": 4, "ClassNameEn": "ItemClass_name_4" },
  { "Class": 5, "ClassNameEn": "ItemClass_name_5" },
  { "Class": 7, "ClassNameEn": "ItemClass_name_7" },
  { "Class": 8, "ClassNameEn": "ItemClass_name_8" },
  { "Class": 10, "ClassNameEn": "ItemClass_name_10" },
  { "Class": 11, "ClassNameEn": "ItemClass_name_11" },
  { "Class": 12, "ClassNameEn": "ItemClass_name_12" },
  { "Class": 13, "ClassNameEn": "ItemClass_name_13" },
  { "Class": 14, "ClassNameEn": "ItemClass_name_14" },
  { "Class": 15, "ClassNameEn": "ItemClass_name_15" },
  { "Class": 29, "ClassNameEn": "ItemClass_name_29" },
  { "Class": 31, "ClassNameEn": "ItemClass_name_31" },
  { "Class": 32, "ClassNameEn": "ItemClass_name_32" },
  { "Class": 33, "ClassNameEn": "ItemClass_name_33" }
]
